kisters/water/hydraulic_network/visualization/bokeh/__init__.py
kisters/water/hydraulic_network/visualization/bokeh/network_viewer.py
kisters.water.hydraulic_network.visualization-0.0.1.dist-info/METADATA
kisters.water.hydraulic_network.visualization-0.0.1.dist-info/WHEEL
kisters.water.hydraulic_network.visualization-0.0.1.dist-info/top_level.txt
kisters.water.hydraulic_network.visualization-0.0.1.dist-info/RECORD
