Metadata-Version: 2.1
Name: kisters.water.hydraulic-network.visualization
Version: 0.0.1
Summary: Visualization library for the Kisters Hydraulic Network Storage service
Home-page: https://gitlab.com/kisters/water/hydraulic-network/visualization
Author: Jesse VanderWees
Author-email: jesse.vanderwees@kisters-bv.nl
License: UNKNOWN
Platform: UNKNOWN
Classifier: Programming Language :: Python :: 3
Classifier: License :: OSI Approved :: GNU Lesser General Public License v2 or later (LGPLv2+)
Classifier: Operating System :: OS Independent
Requires-Dist: bokeh
Requires-Dist: kisters.water.hydraulic-network.client
Requires-Dist: kisters.water.hydraulic-network.models
Requires-Dist: numpy
Requires-Dist: scipy
